unipercept_reward/__init__.py
unipercept_reward/inferencer.py
unipercept_reward/internvl/__init__.py
unipercept_reward/internvl/conversation.py
unipercept_reward/internvl/dist_utils.py
unipercept_reward/internvl/model/__init__.py
unipercept_reward/internvl/model/internlm2/__init__.py
unipercept_reward/internvl/model/internlm2/configuration_internlm2.py
unipercept_reward/internvl/model/internlm2/modeling_internlm2.py
unipercept_reward/internvl/model/internlm2/tokenization_internlm2.py
unipercept_reward/internvl/model/internlm2/tokenization_internlm2_fast.py
unipercept_reward/internvl/model/internvl_chat/__init__.py
unipercept_reward/internvl/model/internvl_chat/aes_tokens.py
unipercept_reward/internvl/model/internvl_chat/configuration_intern_vit.py
unipercept_reward/internvl/model/internvl_chat/configuration_internvl_chat.py
unipercept_reward/internvl/model/internvl_chat/modeling_intern_vit.py
unipercept_reward/internvl/model/internvl_chat/modeling_unipercept.py
unipercept_reward/internvl/model/phi3/__init__.py
unipercept_reward/internvl/model/phi3/configuration_phi3.py
unipercept_reward/internvl/model/phi3/modeling_phi3.py
unipercept_reward-1.0.3.dist-info/METADATA
unipercept_reward-1.0.3.dist-info/WHEEL
unipercept_reward-1.0.3.dist-info/top_level.txt
unipercept_reward-1.0.3.dist-info/RECORD
