Metadata-Version: 2.4
Name: unipercept-reward
Version: 1.0.3
Summary: UniPercept: Towards Unified Perceptual-Level Image Understanding
Home-page: https://github.com/thunderbolt215/UniPercept
Author: Shuo Cao
Classifier: Programming Language :: Python :: 3
Classifier: License :: OSI Approved :: Apache Software License
Classifier: Operating System :: OS Independent
Requires-Python: >=3.8
Requires-Dist: transformers==4.49.0
Requires-Dist: accelerate>=1.10.1
Requires-Dist: datasets>=4.0.0
Requires-Dist: bitsandbytes>=0.47.0
Requires-Dist: peft==0.17.1
Requires-Dist: trl>=0.17.0
Requires-Dist: deepspeed>=0.15.4
Requires-Dist: qwen-vl-utils
Requires-Dist: timm
Requires-Dist: einops
Requires-Dist: decord
Requires-Dist: av
Requires-Dist: pillow
Requires-Dist: numpy
Requires-Dist: pandas
Requires-Dist: scipy
Requires-Dist: latex2sympy2_extended
Requires-Dist: math-verify
Requires-Dist: liger_kernel
Requires-Dist: wandb
Requires-Dist: tensorboardX
Requires-Dist: matplotlib
Requires-Dist: rich
Requires-Dist: tqdm
Requires-Dist: pycocotools
Requires-Dist: python-Levenshtein
Requires-Dist: deep-translator
Requires-Dist: openai
Requires-Dist: httpx[socks]
Requires-Dist: beautifulsoup4
Requires-Dist: torch==2.8.0
Requires-Dist: torchvision==0.23.0
Provides-Extra: flash
Requires-Dist: flash_attn>=2.8.3; extra == "flash"
Dynamic: author
Dynamic: classifier
Dynamic: description
Dynamic: description-content-type
Dynamic: home-page
Dynamic: provides-extra
Dynamic: requires-dist
Dynamic: requires-python
Dynamic: summary
